mincfg/__init__.py
mincfg/configs.py
mincfg/sources/__init__.py
mincfg/sources/abstract.py
mincfg/sources/builtin.py
mincfg/sources/dotenv.py
mincfg/sources/errsrc.py
mincfg/sources/inifilesrc.py
mincfg/sources/meta.py
mincfg/sources/yamlfilesrc.py
mincfg-0.9.dist-info/LICENSE
mincfg-0.9.dist-info/METADATA
mincfg-0.9.dist-info/WHEEL
mincfg-0.9.dist-info/top_level.txt
mincfg-0.9.dist-info/RECORD
