Metadata-Version: 2.1
Name: mincfg
Version: 0.9
Summary: Minimal Application Configuration
Author-email: Paul Jimenez <pj@place.org>
License: GNU GENERAL PUBLIC LICENSE
Project-URL: Homepage, http://github.com/pjz/mincfg
Project-URL: Documentation, http://pjz.github.io/mincfg
Project-URL: Repository, http://github.com/pjz/mincfg.git
Classifier: Development Status :: 5 - Production/Stable
Classifier: Environment :: Console
Classifier: Intended Audience :: Developers
Classifier: Intended Audience :: System Administrators
Classifier: License :: OSI Approved :: GNU General Public License v3 or later (GPLv3+)
Classifier: Natural Language :: English
Classifier: Operating System :: MacOS :: MacOS X
Classifier: Operating System :: Microsoft :: Windows
Classifier: Operating System :: POSIX
Classifier: Programming Language :: Python :: 3.7
Classifier: Programming Language :: Python :: Implementation :: CPython
Requires-Python: >=3.7
License-File: LICENSE
Provides-Extra: all
Requires-Dist: pyyaml ; extra == 'all'
Requires-Dist: configobj ; extra == 'all'
Requires-Dist: python-dotenv ; extra == 'all'
Provides-Extra: dev
Requires-Dist: pytest ; extra == 'dev'
Requires-Dist: pytest-cov ; extra == 'dev'
Requires-Dist: pytest-pylint ; extra == 'dev'
Requires-Dist: pytest-mypy ; extra == 'dev'
Requires-Dist: build ; extra == 'dev'
Requires-Dist: twine ; extra == 'dev'
Requires-Dist: sphinx ; extra == 'dev'
Requires-Dist: furo ; extra == 'dev'
Provides-Extra: env
Requires-Dist: python-dotenv ; extra == 'env'
Provides-Extra: ini
Requires-Dist: configobj ; extra == 'ini'
Provides-Extra: yaml
Requires-Dist: pyyaml ; extra == 'yaml'
